{
    "claims" : [
        {
            "id": "1234568790ABCDE",
            "sequence": 1,
            "links":[
                {
                    "href":"/individuals/losses/TC663795B/loss-claims/1234568790ABCDE",
                    "rel":"self",
                    "method":"GET"
                }
            ]
        },
        {
            "id": "1234568790ABCDF",
            "sequence": 2,
            "links":[
                {
                    "href":"/individuals/losses/TC663795B/loss-claims/1234568790ABCDF",
                    "rel":"self",
                    "method":"GET"
                }
            ]
        }
    ],
    "links":[
        {
            "href":"/individuals/losses/TC663795B/loss-claims",
            "rel":"self",
            "method":"GET"
        },
        {
            "href":"/individuals/losses/TC663795B/loss-claims",
            "rel":"create-loss-claim",
            "method":"POST"
        }
    ]
}